package com.android.email.mail.store;

import com.android.email.mail.*;
import java.nio.charset.*;
import java.util.concurrent.*;
import android.content.*;
import com.android.emailcommon.provider.*;
import com.android.email.*;
import java.util.*;
import com.android.emailcommon.b.*;
import java.nio.*;
import android.text.*;
import java.io.*;
import com.android.emailcommon.mail.*;
import com.android.email.mail.store.imap.*;
import android.os.*;

public class ImapStore extends b
{
    private static final Charset QC;
    static String QD;
    private boolean Pc;
    String QE;
    String QF;
    private final ConcurrentLinkedQueue<a> QG;
    
    static {
        QC = new com.a.a.b().charsetForName("X-RFC-3501");
        ImapStore.QD = null;
    }
    
    private ImapStore(final Context mContext, final Account ml) {
        int pc = 1;
        this.QG = new ConcurrentLinkedQueue<a>();
        this.mContext = mContext;
        this.Ml = ml;
        final HostAuth z = ml.Z(mContext);
        if (z == null) {
            throw new MessagingException("No HostAuth in ImapStore?");
        }
        this.Qb = new com.android.email.mail.transport.b(mContext, "IMAP", z);
        final String[] lq = z.lQ();
        this.Qc = lq[0];
        this.Qd = lq[pc];
        if (z.af(mContext) == null) {
            pc = 0;
        }
        this.Pc = (pc != 0);
        this.QE = z.GZ;
    }
    
    private com.android.email.mail.store.b a(final Context context, final long lq, final String vv, final char zs, final boolean b, Mailbox c) {
        int zr;
        if (c == null) {
            final int c2 = l.c(context, vv);
            c = Mailbox.c(context, lq, vv);
            zr = c2;
        }
        else {
            zr = c.Zr;
        }
        final com.android.email.mail.store.b b2 = (com.android.email.mail.store.b)this.y(vv);
        if (c.lF()) {
            b2.QB = c.lS();
        }
        c.Lq = lq;
        c.Zs = zs;
        final int lastIndex = vv.lastIndexOf(zs);
        String substring;
        if (lastIndex > 0) {
            substring = vv.substring(lastIndex + 1);
        }
        else {
            substring = vv;
        }
        c.Xy = substring;
        if (b) {
            c.dM = 24;
        }
        c.Zu = true;
        c.Vv = vv;
        c.Zr = zr;
        if (b2.QB == null) {
            b2.QB = c.lS();
            c.Zx = 8;
            c.ac(this.mContext);
        }
        b2.Pv = c;
        return b2;
    }
    
    public static String a(final Context p0, final String p1, final String p2, final String p3) {
        // 
        // This method could not be decompiled.
        // 
        // Original Bytecode:
        // 
        //     0: ldc             Lcom/android/email/mail/store/ImapStore;.class
        //     2: monitorenter   
        //     3: getstatic       com/android/email/mail/store/ImapStore.QD:Ljava/lang/String;
        //     6: ifnonnull       375
        //     9: aload_0        
        //    10: ldc             "phone"
        //    12: invokevirtual   android/content/Context.getSystemService:(Ljava/lang/String;)Ljava/lang/Object;
        //    15: checkcast       Landroid/telephony/TelephonyManager;
        //    18: invokevirtual   android/telephony/TelephonyManager.getNetworkOperatorName:()Ljava/lang/String;
        //    21: astore          17
        //    23: aload           17
        //    25: ifnonnull       32
        //    28: ldc             ""
        //    30: astore          17
        //    32: aload_0        
        //    33: invokevirtual   android/content/Context.getPackageName:()Ljava/lang/String;
        //    36: astore          18
        //    38: getstatic       android/os/Build$VERSION.RELEASE:Ljava/lang/String;
        //    41: astore          19
        //    43: getstatic       android/os/Build$VERSION.CODENAME:Ljava/lang/String;
        //    46: astore          20
        //    48: getstatic       android/os/Build.MODEL:Ljava/lang/String;
        //    51: astore          21
        //    53: getstatic       android/os/Build.ID:Ljava/lang/String;
        //    56: astore          22
        //    58: getstatic       android/os/Build.MANUFACTURER:Ljava/lang/String;
        //    61: astore          23
        //    63: ldc             "[^a-zA-Z0-9-_\\+=;:\\.,/ ]"
        //    65: invokestatic    java/util/regex/Pattern.compile:(Ljava/lang/String;)Ljava/util/regex/Pattern;
        //    68: astore          24
        //    70: aload           24
        //    72: aload           18
        //    74: invokevirtual   java/util/regex/Pattern.matcher:(Ljava/lang/CharSequence;)Ljava/util/regex/Matcher;
        //    77: ldc             ""
        //    79: invokevirtual   java/util/regex/Matcher.replaceAll:(Ljava/lang/String;)Ljava/lang/String;
        //    82: astore          25
        //    84: aload           24
        //    86: aload           19
        //    88: invokevirtual   java/util/regex/Pattern.matcher:(Ljava/lang/CharSequence;)Ljava/util/regex/Matcher;
        //    91: ldc             ""
        //    93: invokevirtual   java/util/regex/Matcher.replaceAll:(Ljava/lang/String;)Ljava/lang/String;
        //    96: astore          26
        //    98: aload           24
        //   100: aload           20
        //   102: invokevirtual   java/util/regex/Pattern.matcher:(Ljava/lang/CharSequence;)Ljava/util/regex/Matcher;
        //   105: ldc             ""
        //   107: invokevirtual   java/util/regex/Matcher.replaceAll:(Ljava/lang/String;)Ljava/lang/String;
        //   110: astore          27
        //   112: aload           24
        //   114: aload           21
        //   116: invokevirtual   java/util/regex/Pattern.matcher:(Ljava/lang/CharSequence;)Ljava/util/regex/Matcher;
        //   119: ldc             ""
        //   121: invokevirtual   java/util/regex/Matcher.replaceAll:(Ljava/lang/String;)Ljava/lang/String;
        //   124: astore          28
        //   126: aload           24
        //   128: aload           22
        //   130: invokevirtual   java/util/regex/Pattern.matcher:(Ljava/lang/CharSequence;)Ljava/util/regex/Matcher;
        //   133: ldc             ""
        //   135: invokevirtual   java/util/regex/Matcher.replaceAll:(Ljava/lang/String;)Ljava/lang/String;
        //   138: astore          29
        //   140: aload           24
        //   142: aload           23
        //   144: invokevirtual   java/util/regex/Pattern.matcher:(Ljava/lang/CharSequence;)Ljava/util/regex/Matcher;
        //   147: ldc             ""
        //   149: invokevirtual   java/util/regex/Matcher.replaceAll:(Ljava/lang/String;)Ljava/lang/String;
        //   152: astore          30
        //   154: aload           24
        //   156: aload           17
        //   158: invokevirtual   java/util/regex/Pattern.matcher:(Ljava/lang/CharSequence;)Ljava/util/regex/Matcher;
        //   161: ldc             ""
        //   163: invokevirtual   java/util/regex/Matcher.replaceAll:(Ljava/lang/String;)Ljava/lang/String;
        //   166: astore          31
        //   168: new             Ljava/lang/StringBuilder;
        //   171: dup            
        //   172: ldc             "\"name\" \""
        //   174: invokespecial   java/lang/StringBuilder.<init>:(Ljava/lang/String;)V
        //   177: astore          32
        //   179: aload           32
        //   181: aload           25
        //   183: invokevirtual   java/lang/StringBuilder.append:(Ljava/lang/String;)Ljava/lang/StringBuilder;
        //   186: pop            
        //   187: aload           32
        //   189: ldc             "\""
        //   191: invokevirtual   java/lang/StringBuilder.append:(Ljava/lang/String;)Ljava/lang/StringBuilder;
        //   194: pop            
        //   195: aload           32
        //   197: ldc             " \"os\" \"android\""
        //   199: invokevirtual   java/lang/StringBuilder.append:(Ljava/lang/String;)Ljava/lang/StringBuilder;
        //   202: pop            
        //   203: aload           32
        //   205: ldc             " \"os-version\" \""
        //   207: invokevirtual   java/lang/StringBuilder.append:(Ljava/lang/String;)Ljava/lang/StringBuilder;
        //   210: pop            
        //   211: aload           26
        //   213: invokevirtual   java/lang/String.length:()I
        //   216: ifle            501
        //   219: aload           32
        //   221: aload           26
        //   223: invokevirtual   java/lang/StringBuilder.append:(Ljava/lang/String;)Ljava/lang/StringBuilder;
        //   226: pop            
        //   227: aload           29
        //   229: invokevirtual   java/lang/String.length:()I
        //   232: ifle            251
        //   235: aload           32
        //   237: ldc             "; "
        //   239: invokevirtual   java/lang/StringBuilder.append:(Ljava/lang/String;)Ljava/lang/StringBuilder;
        //   242: pop            
        //   243: aload           32
        //   245: aload           29
        //   247: invokevirtual   java/lang/StringBuilder.append:(Ljava/lang/String;)Ljava/lang/StringBuilder;
        //   250: pop            
        //   251: aload           32
        //   253: ldc             "\""
        //   255: invokevirtual   java/lang/StringBuilder.append:(Ljava/lang/String;)Ljava/lang/StringBuilder;
        //   258: pop            
        //   259: aload           30
        //   261: invokevirtual   java/lang/String.length:()I
        //   264: ifle            291
        //   267: aload           32
        //   269: ldc             " \"vendor\" \""
        //   271: invokevirtual   java/lang/StringBuilder.append:(Ljava/lang/String;)Ljava/lang/StringBuilder;
        //   274: pop            
        //   275: aload           32
        //   277: aload           30
        //   279: invokevirtual   java/lang/StringBuilder.append:(Ljava/lang/String;)Ljava/lang/StringBuilder;
        //   282: pop            
        //   283: aload           32
        //   285: ldc             "\""
        //   287: invokevirtual   java/lang/StringBuilder.append:(Ljava/lang/String;)Ljava/lang/StringBuilder;
        //   290: pop            
        //   291: ldc             "REL"
        //   293: aload           27
        //   295: invokevirtual   java/lang/String.equals:(Ljava/lang/Object;)Z
        //   298: ifeq            334
        //   301: aload           28
        //   303: invokevirtual   java/lang/String.length:()I
        //   306: ifle            334
        //   309: aload           32
        //   311: ldc_w           " \"x-android-device-model\" \""
        //   314: invokevirtual   java/lang/StringBuilder.append:(Ljava/lang/String;)Ljava/lang/StringBuilder;
        //   317: pop            
        //   318: aload           32
        //   320: aload           28
        //   322: invokevirtual   java/lang/StringBuilder.append:(Ljava/lang/String;)Ljava/lang/StringBuilder;
        //   325: pop            
        //   326: aload           32
        //   328: ldc             "\""
        //   330: invokevirtual   java/lang/StringBuilder.append:(Ljava/lang/String;)Ljava/lang/StringBuilder;
        //   333: pop            
        //   334: aload           31
        //   336: invokevirtual   java/lang/String.length:()I
        //   339: ifle            367
        //   342: aload           32
        //   344: ldc_w           " \"x-android-mobile-net-operator\" \""
        //   347: invokevirtual   java/lang/StringBuilder.append:(Ljava/lang/String;)Ljava/lang/StringBuilder;
        //   350: pop            
        //   351: aload           32
        //   353: aload           31
        //   355: invokevirtual   java/lang/StringBuilder.append:(Ljava/lang/String;)Ljava/lang/StringBuilder;
        //   358: pop            
        //   359: aload           32
        //   361: ldc             "\""
        //   363: invokevirtual   java/lang/StringBuilder.append:(Ljava/lang/String;)Ljava/lang/StringBuilder;
        //   366: pop            
        //   367: aload           32
        //   369: invokevirtual   java/lang/StringBuilder.toString:()Ljava/lang/String;
        //   372: putstatic       com/android/email/mail/store/ImapStore.QD:Ljava/lang/String;
        //   375: ldc             Lcom/android/email/mail/store/ImapStore;.class
        //   377: monitorexit    
        //   378: new             Ljava/lang/StringBuilder;
        //   381: dup            
        //   382: getstatic       com/android/email/mail/store/ImapStore.QD:Ljava/lang/String;
        //   385: invokespecial   java/lang/StringBuilder.<init>:(Ljava/lang/String;)V
        //   388: astore          5
        //   390: aload_0        
        //   391: invokestatic    com/android/emailcommon/VendorPolicyLoader.W:(Landroid/content/Context;)Lcom/android/emailcommon/VendorPolicyLoader;
        //   394: aload_1        
        //   395: aload_2        
        //   396: aload_3        
        //   397: invokevirtual   com/android/emailcommon/VendorPolicyLoader.b:(Ljava/lang/String;Ljava/lang/String;Ljava/lang/String;)Ljava/lang/String;
        //   400: astore          6
        //   402: aload           6
        //   404: ifnull          423
        //   407: aload           5
        //   409: bipush          32
        //   411: invokevirtual   java/lang/StringBuilder.append:(C)Ljava/lang/StringBuilder;
        //   414: pop            
        //   415: aload           5
        //   417: aload           6
        //   419: invokevirtual   java/lang/StringBuilder.append:(Ljava/lang/String;)Ljava/lang/StringBuilder;
        //   422: pop            
        //   423: aload_0        
        //   424: invokestatic    com/android/email/r.s:(Landroid/content/Context;)Lcom/android/email/r;
        //   427: invokevirtual   com/android/email/r.gX:()Ljava/lang/String;
        //   430: astore          9
        //   432: ldc_w           "SHA-1"
        //   435: invokestatic    java/security/MessageDigest.getInstance:(Ljava/lang/String;)Ljava/security/MessageDigest;
        //   438: astore          10
        //   440: aload           10
        //   442: aload_1        
        //   443: invokevirtual   java/lang/String.getBytes:()[B
        //   446: invokevirtual   java/security/MessageDigest.update:([B)V
        //   449: aload           10
        //   451: aload           9
        //   453: invokevirtual   java/lang/String.getBytes:()[B
        //   456: invokevirtual   java/security/MessageDigest.update:([B)V
        //   459: aload           10
        //   461: invokevirtual   java/security/MessageDigest.digest:()[B
        //   464: iconst_2       
        //   465: invokestatic    android/util/Base64.encodeToString:([BI)Ljava/lang/String;
        //   468: astore          11
        //   470: aload           5
        //   472: ldc_w           " \"AGUID\" \""
        //   475: invokevirtual   java/lang/StringBuilder.append:(Ljava/lang/String;)Ljava/lang/StringBuilder;
        //   478: pop            
        //   479: aload           5
        //   481: aload           11
        //   483: invokevirtual   java/lang/StringBuilder.append:(Ljava/lang/String;)Ljava/lang/StringBuilder;
        //   486: pop            
        //   487: aload           5
        //   489: bipush          34
        //   491: invokevirtual   java/lang/StringBuilder.append:(C)Ljava/lang/StringBuilder;
        //   494: pop            
        //   495: aload           5
        //   497: invokevirtual   java/lang/StringBuilder.toString:()Ljava/lang/String;
        //   500: areturn        
        //   501: aload           32
        //   503: ldc_w           "1.0"
        //   506: invokevirtual   java/lang/StringBuilder.append:(Ljava/lang/String;)Ljava/lang/StringBuilder;
        //   509: pop            
        //   510: goto            227
        //   513: astore          4
        //   515: ldc             Lcom/android/email/mail/store/ImapStore;.class
        //   517: monitorexit    
        //   518: aload           4
        //   520: athrow         
        //   521: astore          7
        //   523: getstatic       com/android/emailcommon/b.mW:Ljava/lang/String;
        //   526: ldc_w           "couldn't obtain SHA-1 hash for device UID"
        //   529: iconst_0       
        //   530: anewarray       Ljava/lang/Object;
        //   533: invokestatic    com/android/mail/utils/E.c:(Ljava/lang/String;Ljava/lang/String;[Ljava/lang/Object;)I
        //   536: pop            
        //   537: goto            495
        //    Exceptions:
        //  Try           Handler
        //  Start  End    Start  End    Type                                    
        //  -----  -----  -----  -----  ----------------------------------------
        //  3      23     513    521    Any
        //  32     227    513    521    Any
        //  227    251    513    521    Any
        //  251    291    513    521    Any
        //  291    334    513    521    Any
        //  334    367    513    521    Any
        //  367    375    513    521    Any
        //  375    378    513    521    Any
        //  423    495    521    540    Ljava/security/NoSuchAlgorithmException;
        //  501    510    513    521    Any
        // 
        // The error that occurred was:
        // 
        // java.lang.IllegalStateException: Expression is linked from several locations: Label_0423:
        //     at com.strobel.decompiler.ast.Error.expressionLinkedFromMultipleLocations(Error.java:27)
        //     at com.strobel.decompiler.ast.AstOptimizer.mergeDisparateObjectInitializations(AstOptimizer.java:2592)
        //     at com.strobel.decompiler.ast.AstOptimizer.optimize(AstOptimizer.java:235)
        //     at com.strobel.decompiler.ast.AstOptimizer.optimize(AstOptimizer.java:42)
        //     at com.strobel.decompiler.languages.java.ast.AstMethodBodyBuilder.createMethodBody(AstMethodBodyBuilder.java:214)
        //     at com.strobel.decompiler.languages.java.ast.AstMethodBodyBuilder.createMethodBody(AstMethodBodyBuilder.java:99)
        //     at com.strobel.decompiler.languages.java.ast.AstBuilder.createMethodBody(AstBuilder.java:757)
        //     at com.strobel.decompiler.languages.java.ast.AstBuilder.createMethod(AstBuilder.java:655)
        //     at com.strobel.decompiler.languages.java.ast.AstBuilder.addTypeMembers(AstBuilder.java:532)
        //     at com.strobel.decompiler.languages.java.ast.AstBuilder.createTypeCore(AstBuilder.java:499)
        //     at com.strobel.decompiler.languages.java.ast.AstBuilder.createTypeNoCache(AstBuilder.java:141)
        //     at com.strobel.decompiler.languages.java.ast.AstBuilder.createType(AstBuilder.java:130)
        //     at com.strobel.decompiler.languages.java.ast.AstBuilder.addType(AstBuilder.java:105)
        //     at com.strobel.decompiler.languages.java.JavaLanguage.buildAst(JavaLanguage.java:71)
        //     at com.strobel.decompiler.languages.java.JavaLanguage.decompileType(JavaLanguage.java:59)
        //     at com.strobel.decompiler.DecompilerDriver.decompileType(DecompilerDriver.java:304)
        //     at com.strobel.decompiler.DecompilerDriver.decompileJar(DecompilerDriver.java:225)
        //     at com.strobel.decompiler.DecompilerDriver.main(DecompilerDriver.java:110)
        // 
        throw new IllegalStateException("An error occurred while decompiling this method.");
    }
    
    static String a(final Message[] array) {
        int i = 0;
        final StringBuilder sb = new StringBuilder();
        final int length = array.length;
        int n = 0;
        while (i < length) {
            final Message message = array[i];
            if (n != 0) {
                sb.append(',');
            }
            sb.append(message.ln());
            n = 1;
            ++i;
        }
        return sb.toString();
    }
    
    private static void a(final Context context, final HashMap<String, com.android.email.mail.store.b> hashMap) {
        final Iterator<com.android.email.mail.store.b> iterator = hashMap.values().iterator();
        while (iterator.hasNext()) {
            iterator.next().C(context);
        }
    }
    
    private static void b(final HashMap<String, com.android.email.mail.store.b> hashMap) {
        for (final String s : hashMap.keySet()) {
            final Mailbox pv = hashMap.get(s).Pv;
            final int lastIndex = pv.Vv.lastIndexOf(pv.Zs);
            long ln = -1L;
            String zp;
            if (lastIndex != -1) {
                final String substring = s.substring(0, lastIndex);
                if ("INBOX".equalsIgnoreCase(substring)) {
                    zp = "INBOX";
                }
                else {
                    zp = substring;
                }
                final com.android.email.mail.store.b b = hashMap.get(zp);
                Mailbox pv2;
                if (b == null) {
                    pv2 = null;
                }
                else {
                    pv2 = b.Pv;
                }
                if (pv2 != null) {
                    ln = pv2.Ln;
                    pv2.dM |= 0x3;
                }
            }
            else {
                zp = null;
            }
            pv.Zq = ln;
            pv.Zp = zp;
        }
    }
    
    static String c(String string, final String s) {
        if ("INBOX".equalsIgnoreCase(string)) {
            return string;
        }
        if (s != null) {
            string = s + string;
        }
        final ByteBuffer encode = ImapStore.QC.encode(string);
        final byte[] array = new byte[encode.limit()];
        encode.get(array);
        return s.a(array);
    }
    
    static String d(final String s, final String s2) {
        String s3 = ImapStore.QC.decode(ByteBuffer.wrap(s.aG(s))).toString();
        if (s2 != null && s3.startsWith(s2)) {
            s3 = s3.substring(s2.length());
        }
        return s3;
    }
    
    public static b newInstance(final Account account, final Context context) {
        return new ImapStore(context, account);
    }
    
    final void D(final String qf) {
        this.QF = qf;
    }
    
    final void E(final String qe) {
        this.QE = qe;
    }
    
    final void a(final a a) {
        if (a != null) {
            a.iQ();
            this.QG.add(a);
        }
    }
    
    @Override
    public final boolean aU(final int n) {
        switch (n) {
            default: {
                return false;
            }
            case 0:
            case 1:
            case 5:
            case 6:
            case 7: {
                return true;
            }
        }
    }
    
    final Context getContext() {
        return this.mContext;
    }
    
    final String getPassword() {
        return this.Qd;
    }
    
    final String getUsername() {
        return this.Qc;
    }
    
    @Override
    public final Folder[] iK() {
    Label_0194_Outer:
        while (true) {
            final a jj = this.jj();
            while (true) {
                try {
                    final HashMap<String, com.android.email.mail.store.b> hashMap = new HashMap<String, com.android.email.mail.store.b>();
                    jj.z("NOOP");
                    String string = "LIST \"\" \"*\"";
                    if (this.QE != null) {
                        string = "LIST \"\" \"" + this.QE + "*\"";
                    }
                    for (final g g : jj.z(string)) {
                        if (g.c(0, "LIST")) {
                            final i az = g.aZ(3);
                            if (az.isEmpty()) {
                                continue Label_0194_Outer;
                            }
                            final String d = d(az.getString(), this.QE);
                            if ("INBOX".equalsIgnoreCase(d)) {
                                continue Label_0194_Outer;
                            }
                            if (g.aY(1).contains("\\NOSELECT")) {
                                goto Label_0264;
                            }
                            final boolean b = true;
                            final String string2 = g.aZ(2).getString();
                            if (TextUtils.isEmpty((CharSequence)string2)) {}
                            final char char1 = string2.charAt(0);
                            hashMap.put(d, this.a(this.mContext, this.Ml.Ln, d, char1, b, null));
                        }
                    }
                    goto Label_0270;
                }
                catch (IOException ex) {
                    jj.close();
                    throw new MessagingException("Unable to get folder list", ex);
                }
                catch (AuthenticationFailedException ex2) {
                    jj.iQ();
                    try {
                        throw ex2;
                    }
                    finally {}
                }
                final char char1 = '\0';
                continue;
            }
        }
    }
    
    @Override
    public final Bundle iL() {
        int n = -1;
        final Bundle bundle = new Bundle();
        final a a = new a(this);
        while (true) {
            try {
                a.open();
                a.close();
                a.iQ();
                bundle.putInt("validate_result_code", n);
                return bundle;
            }
            catch (IOException ex) {
                bundle.putString("validate_error_message", ex.getMessage());
                n = 1;
                a.iQ();
                continue;
            }
            finally {
                a.iQ();
            }
            break;
        }
    }
    
    @Override
    public final void iM() {
        while (true) {
            final a a = this.QG.poll();
            if (a == null) {
                break;
            }
            a.close();
        }
    }
    
    final boolean jf() {
        return this.Pc;
    }
    
    final boolean jg() {
        return TextUtils.isEmpty((CharSequence)this.QF) && !TextUtils.isEmpty((CharSequence)this.QE);
    }
    
    final com.android.email.mail.transport.b jh() {
        return this.Qb.jU();
    }
    
    final void ji() {
        if (!TextUtils.isEmpty((CharSequence)this.QE) && !TextUtils.isEmpty((CharSequence)this.QF) && !this.QE.endsWith(this.QF)) {
            this.QE += this.QF;
        }
    }
    
    final a jj() {
        a a = this.QG.poll();
        Label_0028: {
            if (a == null) {
                break Label_0028;
            }
            try {
                a.a(this);
                a.z("NOOP");
                if (a == null) {
                    a = new a(this);
                }
                return a;
            }
            catch (IOException ex) {}
            catch (MessagingException ex2) {
                goto Label_0044;
            }
        }
    }
    
    @Override
    public final Folder y(final String s) {
        return new com.android.email.mail.store.b(this, s);
    }
}
